fine_python_aksem/__init__.py
fine_python_aksem/preset.toml
fine_python_aksem-0.3.0a3.dist-info/licenses/LICENSE
fine_python_aksem-0.3.0a3.dist-info/METADATA
fine_python_aksem-0.3.0a3.dist-info/WHEEL
fine_python_aksem-0.3.0a3.dist-info/top_level.txt
fine_python_aksem-0.3.0a3.dist-info/RECORD
