Metadata-Version: 2.4
Name: fine_python_aksem
Version: 0.3.0a3
Author-email: Vladyslav Hnatiuk <aders1234@gmail.com>
Requires-Python: <=3.14,>=3.11
License-File: LICENSE
Requires-Dist: finecode_extension_api~=0.4.0a0
Dynamic: license-file
